klaviyo/__init__.py
klaviyo/client.py
klaviyo/core/__init__.py
klaviyo/core/api_error.py
klaviyo/core/client_wrapper.py
klaviyo/core/datetime_utils.py
klaviyo/core/jsonable_encoder.py
klaviyo/core/remove_none_from_dict.py
klaviyo/environment.py
klaviyo/py.typed
klaviyo/resources/__init__.py
klaviyo/resources/accounts/__init__.py
klaviyo/resources/accounts/client.py
klaviyo/resources/campaigns/__init__.py
klaviyo/resources/campaigns/client.py
klaviyo/resources/catalogs/__init__.py
klaviyo/resources/catalogs/client.py
klaviyo/resources/client/__init__.py
klaviyo/resources/client/client.py
klaviyo/resources/data_privacy/__init__.py
klaviyo/resources/data_privacy/client.py
klaviyo/resources/events/__init__.py
klaviyo/resources/events/client.py
klaviyo/resources/flows/__init__.py
klaviyo/resources/flows/client.py
klaviyo/resources/lists/__init__.py
klaviyo/resources/lists/client.py
klaviyo/resources/metrics/__init__.py
klaviyo/resources/metrics/client.py
klaviyo/resources/profiles/__init__.py
klaviyo/resources/profiles/client.py
klaviyo/resources/segments/__init__.py
klaviyo/resources/segments/client.py
klaviyo/resources/tags/__init__.py
klaviyo/resources/tags/client.py
klaviyo/resources/templates/__init__.py
klaviyo/resources/templates/client.py
klaviyo/types/__init__.py
klaviyo/types/account_enum.py
klaviyo/types/account_response_object_resource.py
klaviyo/types/account_response_object_resource_attributes.py
klaviyo/types/api_job_error_payload.py
klaviyo/types/audiences_sub_object.py
klaviyo/types/back_in_stock_subscription_enum.py
klaviyo/types/base_event_create_query_resource_object.py
klaviyo/types/base_event_create_query_resource_object_attributes.py
klaviyo/types/base_event_create_query_resource_object_attributes_metric.py
klaviyo/types/campaign_clone_query_resource_object.py
klaviyo/types/campaign_clone_query_resource_object_attributes.py
klaviyo/types/campaign_create_query_resource_object.py
klaviyo/types/campaign_create_query_resource_object_attributes.py
fern_klaviyo-0.0.15.dist-info/METADATA
fern_klaviyo-0.0.15.dist-info/WHEEL
fern_klaviyo-0.0.15.dist-info/RECORD
